{"_ts":[1538372569],"_r":{"breakdown":{"html":{"bytes":[36502],"requests":[4]},"js":{"bytes":[345948],"requests":[16]},"css":{"bytes":[61060],"requests":[3]},"image":{"bytes":[3957736],"requests":[68]},"flash":{"bytes":[0],"requests":[0]},"font":{"bytes":[34816],"requests":[4]},"video":{"bytes":[0],"requests":[0]},"other":{"bytes":[0],"requests":[0]}},"date":[1538372569],"domElements":[762],"domInteractive":[1596.5],"firstPaint":[1514.3000000025],"fullyLoaded":[8659],"id":["181001_VK_b4d6661c42d242c6d7dfff09d2e4f230"],"loadTime":[8419],"render":[1500],"SpeedIndex":[1512],"TTFB":[559],"videoFrames":[[{"_i":"ms_000000.jpg","_t":0,"_vc":0},{"_i":"ms_001500.jpg","_t":1500,"_vc":94},{"_i":"ms_001700.jpg","_t":1700,"_vc":100}]],"visualComplete":[1700],"lighthouse":[35],"pagespeed":[54]}}