{"_ts":[1488327505,1488368324,1488368758],"_r":{"breakdown":{"html":{"bytes":[21383,19870,20671],"requests":[5,5,5]},"js":{"bytes":[132835,132778,132830],"requests":[11,11,11]},"css":{"bytes":[58161,58334,58334],"requests":[1,1,1]},"image":{"bytes":[3180644,3180593,3180724],"requests":[46,46,46]},"flash":{"bytes":[0,0,0],"requests":[0,0,0]},"font":{"bytes":[70040,70040,70040],"requests":[4,4,4]},"other":{"bytes":[0,0,0],"requests":[0,0,0]}},"date":[1488327505,1488368324,1488368758],"domElements":[570,570,570],"domInteractive":[2396,2074,2169],"firstPaint":[1451.5,1427.5,1431],"fullyLoaded":[6788.5,6707,6680],"id":["170301_EP_Q4","170301_6M_MC3","170301_FQ_N0E"],"loadTime":[6628,6549,6530],"render":[1536,1577.5,1835],"SpeedIndex":[1773.5,1705.5,2033],"TTFB":[472.5,411.5,422],"videoFrames":[[{"_t":0,"_vc":0},{"_t":1500,"_vc":76},{"_t":2300,"_vc":96},{"_t":2600,"_vc":96},{"_t":2800,"_vc":100}],[{"_t":0,"_vc":0},{"_t":1600,"_vc":94},{"_t":2700,"_vc":96},{"_t":4200,"_vc":96},{"_t":4600,"_vc":100}],[{"_t":0,"_vc":0},{"_t":2200,"_vc":94},{"_t":2700,"_vc":96},{"_t":4100,"_vc":96},{"_t":4700,"_vc":100}]],"visualComplete":[3736.5,4582.5,4642]}}